sparc.sa-1.3.2-py2.7-nspkg.pth
sparc/sa/__init__.py
sparc/sa/configure.zcml
sparc/sa/ftesting.zcml
sparc/sa/testing.py
sparc/sa/engine/__init__.py
sparc/sa/engine/configure.yaml
sparc/sa/engine/configure.zcml
sparc/sa/engine/engine.py
sparc/sa/engine/interfaces.py
sparc/sa/engine/tests/__init__.py
sparc/sa/engine/tests/test_engine.py
sparc/sa/ext/__init__.py
sparc/sa/ext/interfaces.py
sparc/sa/ext/tests/__init__.py
sparc/sa/ext/tests/test_interfaces.py
sparc/sa/orm/__init__.py
sparc/sa/orm/configure.zcml
sparc/sa/orm/interfaces.py
sparc/sa/orm/session.py
sparc/sa/orm/testing.py
sparc/sa/orm/attributes/__init__.py
sparc/sa/orm/attributes/configure.zcml
sparc/sa/orm/attributes/interfaces.py
sparc/sa/orm/attributes/mapping.py
sparc/sa/orm/attributes/tests/__init__.py
sparc/sa/orm/attributes/tests/test_interfaces.py
sparc/sa/orm/attributes/tests/test_mapping.py
sparc/sa/orm/mapper/__init__.py
sparc/sa/orm/mapper/interfaces.py
sparc/sa/orm/mapper/tests/__init__.py
sparc/sa/orm/mapper/tests/test_interfaces.py
sparc/sa/orm/query/__init__.py
sparc/sa/orm/query/configure.zcml
sparc/sa/orm/query/filter.py
sparc/sa/orm/query/filter.zcml
sparc/sa/orm/query/interfaces.py
sparc/sa/orm/query/query.py
sparc/sa/orm/query/result.py
sparc/sa/orm/query/result.zcml
sparc/sa/orm/query/sequence.py
sparc/sa/orm/query/testing.py
sparc/sa/orm/query/tests/__init__.py
sparc/sa/orm/query/tests/test_interfaces.py
sparc/sa/orm/query/tests/test_query.py
sparc/sa/orm/query/tests/test_sequence.py
sparc/sa/orm/tests/__init__.py
sparc/sa/orm/tests/test_session.py
sparc.sa-1.3.2.dist-info/DESCRIPTION.rst
sparc.sa-1.3.2.dist-info/METADATA
sparc.sa-1.3.2.dist-info/RECORD
sparc.sa-1.3.2.dist-info/WHEEL
sparc.sa-1.3.2.dist-info/entry_points.txt
sparc.sa-1.3.2.dist-info/metadata.json
sparc.sa-1.3.2.dist-info/namespace_packages.txt
sparc.sa-1.3.2.dist-info/top_level.txt
